indian_pincode_details/__init__.py
indian_pincode_details/pincodes.bz2
indian_pincode_details/pincodes.json
indian_pincode_details/__pycache__/__init__.cpython-311.pyc
indian_pincode_details-0.0.1.dist-info/LICENSE
indian_pincode_details-0.0.1.dist-info/METADATA
indian_pincode_details-0.0.1.dist-info/WHEEL
indian_pincode_details-0.0.1.dist-info/top_level.txt
indian_pincode_details-0.0.1.dist-info/RECORD
